v/__init__.py
v/colour.py
v/file.py
v/maths.py
vitalpy-2.8.dist-info/LICENSE
vitalpy-2.8.dist-info/METADATA
vitalpy-2.8.dist-info/WHEEL
vitalpy-2.8.dist-info/top_level.txt
vitalpy-2.8.dist-info/RECORD
