Metadata-Version: 2.1
Name: vitalpy
Version: 2.8
Summary: vitalpy - the ultimate package for everything
Author-email: Dylan Rogers <opendylan@proton.me>
Project-URL: Homepage, http://123web.uk/vitalpy
Project-URL: Bug Tracker, http://123web.uk/vitalpy
Classifier: Programming Language :: Python
Classifier: License :: OSI Approved :: MIT License
Classifier: Operating System :: OS Independent
Requires-Python: >=2.0
License-File: LICENSE
